audig/__init__.py
audig/mixer.py
audig/paths.py
audig-0.2.0.dist-info/METADATA
audig-0.2.0.dist-info/WHEEL
audig-0.2.0.dist-info/RECORD
