Metadata-Version: 2.1
Name: audig
Version: 0.2.0
Summary: Reprodutor de áudio para estudo de inglês.
Author: Oseiasdfarias
Author-email: oseias.dfarias@gmail.com
Requires-Python: >=3.8.1,<3.11
Classifier: Programming Language :: Python :: 3
Classifier: Programming Language :: Python :: 3.9
Classifier: Programming Language :: Python :: 3.10
Requires-Dist: audioread (>=3.0.0,<4.0.0)
Requires-Dist: mkdocs (>=1.4.2,<2.0.0)
Requires-Dist: mkdocs-material (>=9.1.1,<10.0.0)
Requires-Dist: mkdocstrings[python] (>=0.20.0,<0.21.0)
Requires-Dist: pygame (>=2.2.0,<3.0.0)
Requires-Dist: pymdown-extensions (>=9.10,<10.0)
